butterfly/__about__.py
butterfly/__init__.py
butterfly/butterfly.conf.default
butterfly/escapes.py
butterfly/pam.py
butterfly/routes.py
butterfly/terminal.py
butterfly/utils.py
butterfly/bin/cat.py
butterfly/bin/colors.py
butterfly/bin/help.py
butterfly/bin/html.py
butterfly/bin/open.py
butterfly/bin/session.py
butterfly/sass/_16_colors.sass
butterfly/sass/_256_colors.sass
butterfly/sass/_all_fx.sass
butterfly/sass/_colors.sass
butterfly/sass/_cursor.sass
butterfly/sass/_font.sass
butterfly/sass/_layout.sass
butterfly/sass/_light_fx.sass
butterfly/sass/_styles.sass
butterfly/sass/_term_styles.sass
butterfly/sass/_text_fx.sass
butterfly/sass/_variables.sass
butterfly/sass/main.sass
butterfly/static/ext.min.js
butterfly/static/html-sanitizer.js
butterfly/static/main.css
butterfly/static/main.min.js
butterfly/static/fonts/SIL Open Font License.txt
butterfly/static/fonts/SourceCodePro-Black.otf
butterfly/static/fonts/SourceCodePro-Bold.otf
butterfly/static/fonts/SourceCodePro-ExtraLight.otf
butterfly/static/fonts/SourceCodePro-Light.otf
butterfly/static/fonts/SourceCodePro-Medium.otf
butterfly/static/fonts/SourceCodePro-Regular.otf
butterfly/static/fonts/SourceCodePro-Semibold.otf
butterfly/static/images/favicon.png
butterfly/templates/index.html
butterfly/templates/motd
butterfly/themes/README.md
butterfly/themes/C64/_font.sass
butterfly/themes/C64/style.sass
butterfly/themes/C64/font/C64_Pro_Mono-STYLE.woff
butterfly/themes/DOS/Perfect DOS VGA 437 Win.woff
butterfly/themes/DOS/style.sass
butterfly/themes/abstract-image/style.sass
butterfly/themes/abstract-image/image/abstract_bg.jpg
butterfly/themes/color-base16-dark/style.sass
butterfly/themes/color-base16-light/style.sass
butterfly/themes/color-dracula/style.sass
butterfly/themes/color-monokai/style.sass
butterfly/themes/color-mostly-bright/style.sass
butterfly/themes/color-neon/style.sass
butterfly/themes/color-oceanic/style.sass
butterfly-3.2.5.dist-info/METADATA
butterfly-3.2.5.dist-info/RECORD
butterfly-3.2.5.dist-info/WHEEL
butterfly-3.2.5.dist-info/top_level.txt
